__init__.py
_version.py
exchange.py
venrate.py
platforms/__init__.py
platforms/bcv.py
platforms/binance.py
platforms/monitordolar.py
platforms/yadio.py
venrate-1.0.4.dist-info/COPYING
venrate-1.0.4.dist-info/LICENSE
venrate-1.0.4.dist-info/METADATA
venrate-1.0.4.dist-info/WHEEL
venrate-1.0.4.dist-info/top_level.txt
venrate-1.0.4.dist-info/RECORD
