Metadata-Version: 2.1
Name: venrate
Version: 1.0.4
Summary: Venrate get exchange rates from different platforms
Author-email: sivefunc <sivefunc@tuta.io>
License: venrate - exchange rates from multiple platforms
Project-URL: Homepage, https://gitlab.com/sivefunc/
Keywords: bcv,exchange,api,venezuela,http,monitordolar,binance,yadio
Classifier: License :: OSI Approved :: GNU General Public License v3 (GPLv3)
Classifier: Programming Language :: Python
Classifier: Programming Language :: Python :: 3
Requires-Python: >=3.9
License-File: LICENSE
License-File: COPYING
Requires-Dist: requests>=2.32.3
